refactorlib/__init__.py
refactorlib/dictnode.py
refactorlib/filetypes.py
refactorlib/node.py
refactorlib/parse.py
refactorlib/refactor.py
refactorlib/util.py
refactorlib/cheetah/__init__.py
refactorlib/cheetah/node.py
refactorlib/cheetah/parse.py
refactorlib/cheetah/unparse.py
refactorlib/cheetah/plugins/__init__.py
refactorlib/cli/__init__.py
refactorlib/cli/xmlfrom.py
refactorlib/cli/xmlstrip.py
refactorlib/javascript/__init__.py
refactorlib/javascript/parse.py
refactorlib/javascript/reflectjs.js
refactorlib/python/__init__.py
refactorlib/python/parse.py
refactorlib/python/plugins/__init__.py
refactorlib-0.15.0.dist-info/METADATA
refactorlib-0.15.0.dist-info/WHEEL
refactorlib-0.15.0.dist-info/entry_points.txt
refactorlib-0.15.0.dist-info/top_level.txt
refactorlib-0.15.0.dist-info/RECORD
